ImageMagic/Aocr.py
ImageMagic/Atesseract.py
ImageMagic/Image.py
ImageMagic/_Atesseract.py
ImageMagic/__init__.py
ImageMagic/_version.py
src/__init__.py
src/ImageMagic/Aocr.py
src/ImageMagic/Atesseract.py
src/ImageMagic/Image.py
src/ImageMagic/__init__.py
src/ImageMagic/_version.py
test/__init__.py
test/test.py
ImageMagic-0.2.1.dist-info/LICENSE
ImageMagic-0.2.1.dist-info/METADATA
ImageMagic-0.2.1.dist-info/WHEEL
ImageMagic-0.2.1.dist-info/top_level.txt
ImageMagic-0.2.1.dist-info/RECORD
