Metadata-Version: 2.1
Name: ImageMagic
Version: 0.2.1
Summary: 图像处理库（包括但不限于图像）【Image processing libraries (including but not limited to images)】
Home-page: https://github.com/asxez/ImageMagic
Author: asxe
Author-email: 2973918177@qq.com
License: GNU GPL 3.0
Keywords: Python library,image process,imagemagic,ocr function and more!
License-File: LICENSE
